fdecimal/__init__.py
fdecimal/fdecimal.py
fdecimal-0.2.0.dist-info/DESCRIPTION.rst
fdecimal-0.2.0.dist-info/METADATA
fdecimal-0.2.0.dist-info/metadata.json
fdecimal-0.2.0.dist-info/RECORD
fdecimal-0.2.0.dist-info/top_level.txt
fdecimal-0.2.0.dist-info/WHEEL
