Metadata-Version: 1.1
Name: fdecimal
Version: 0.2.0
Summary: Decimal compatability with float
Home-page: https://github.com/bennylope/fdecimal
Author: Ben Lopatin
Author-email: ben@benlopatin.com
License: BSD
Keywords: fdecimal
Platform: UNKNOWN
Classifier: Development Status :: 2 - Pre-Alpha
Classifier: Intended Audience :: Developers
Classifier: License :: OSI Approved :: BSD License
Classifier: Natural Language :: English
Classifier: Programming Language :: Python :: 2
Classifier: Programming Language :: Python :: 2.7
